Alpha_Vantage_API_Data/API_Data_Retrieves.py
Alpha_Vantage_API_Data/__init__.py
Alpha_Vantage_API_Data-1.0.3.dist-info/LICENSE
Alpha_Vantage_API_Data-1.0.3.dist-info/METADATA
Alpha_Vantage_API_Data-1.0.3.dist-info/WHEEL
Alpha_Vantage_API_Data-1.0.3.dist-info/top_level.txt
Alpha_Vantage_API_Data-1.0.3.dist-info/RECORD
