Metadata-Version: 2.1
Name: Alpha_Vantage_API_Data
Version: 1.0.3
Summary: This is an Aplha_Vantage_API data retrieving package
Home-page: https://github.com/codemakerss/Alpha_Vantage_API_Project
Author: Jeff Duan
License: UNKNOWN
Project-URL: Bug Tracker, https://github.com/codemakerss/Alpha_Vantage_API_Project/issues
Platform: UNKNOWN
Classifier: Natural Language :: English
Classifier: Programming Language :: Python :: 3.6
Classifier: License :: OSI Approved :: MIT License
Classifier: Operating System :: MacOS
Requires-Python: >=3.6
License-File: LICENSE
